streamlabsio/__init__.py
streamlabsio/client.py
streamlabsio/error.py
streamlabsio/models.py
streamlabsio-1.1.3.dist-info/LICENSE
streamlabsio-1.1.3.dist-info/METADATA
streamlabsio-1.1.3.dist-info/WHEEL
streamlabsio-1.1.3.dist-info/RECORD
