Metadata-Version: 2.3
Name: streamlabsio
Version: 1.1.3
Summary: Get real time Twitch/Youtube events through Streamlabs SocketIO API
License: MIT
Author: Onyx and Iris
Author-email: code@onyxandiris.online
Requires-Python: >=3.8
Classifier: License :: OSI Approved :: MIT License
Classifier: Programming Language :: Python :: 3
Classifier: Programming Language :: Python :: 3.8
Classifier: Programming Language :: Python :: 3.9
Classifier: Programming Language :: Python :: 3.10
Classifier: Programming Language :: Python :: 3.11
Classifier: Programming Language :: Python :: 3.12
Classifier: Programming Language :: Python :: 3.13
Requires-Dist: observable (>=1.0.3,<2.0.0)
Requires-Dist: python-engineio (==3.14.2)
Requires-Dist: python-socketio[client] (==4.6.0)
Requires-Dist: tomli (>=2.0.1,<3.0) ; python_version < "3.11"
